LICENSE.txt
README.txt
restlib.py
setup.cfg
setup.py
docs/HISTORY.txt
restlib.egg-info/PKG-INFO
restlib.egg-info/SOURCES.txt
restlib.egg-info/dependency_links.txt
restlib.egg-info/entry_points.txt
restlib.egg-info/top_level.txt
restlib.egg-info/zip-safe